{
  "src/data/text/easy_chat/groups/status/words.h": {
    "string_0": "DARK$",
    "string_1": "STENCH$",
    "string_2": "THICK FAT$",
    "string_3": "RAIN DISH$",
    "string_4": "DRIZZLE$",
    "string_5": "ARENA TRAP$",
    "string_6": "INTIMIDATE$",
    "string_7": "ROCK HEAD$",
    "string_8": "COLOR$",
    "string_9": "ALT. COLOR$",
    "string_10": "ROCK$",
    "string_11": "BEAUTIFUL$",
    "string_12": "BEAUTY$",
    "string_13": "AIR LOCK$",
    "string_14": "PSYCHIC$",
    "string_15": "HYPER CUTTER$",
    "string_16": "FIGHTING$",
    "string_17": "SHADOW TAG$",
    "string_18": "SMART$",
    "string_19": "SMARTNESS$",
    "string_20": "SPEED BOOST$",
    "string_21": "COOL$",
    "string_22": "COOLNESS$",
    "string_23": "BATTLE ARMOR$",
    "string_24": "CUTE$",
    "string_25": "CUTENESS$",
    "string_26": "STURDY$",
    "string_27": "SUCTION CUPS$",
    "string_28": "GRASS$",
    "string_29": "CLEAR BODY$",
    "string_30": "TORRENT$",
    "string_31": "GHOST$",
    "string_32": "ICE$",
    "string_33": "GUTS$",
    "string_34": "ROUGH SKIN$",
    "string_35": "SHELL ARMOR$",
    "string_36": "NATURAL CURE$",
    "string_37": "DAMP$",
    "string_38": "GROUND$",
    "string_39": "LIMBER$",
    "string_40": "MAGNET PULL$",
    "string_41": "WHITE SMOKE$",
    "string_42": "SYNCHRONIZE$",
    "string_43": "OVERGROW$",
    "string_44": "SWIFT SWIM$",
    "string_45": "SAND STREAM$",
    "string_46": "SAND VEIL$",
    "string_47": "KEEN EYE$",
    "string_48": "INNERFOCUS$",
    "string_49": "STATIC$",
    "string_50": "TYPE$",
    "string_51": "TOUGH$",
    "string_52": "TOUGHNESS$",
    "string_53": "SHED SKIN$",
    "string_54": "HUGE POWER$",
    "string_55": "VOLT ABSORB$",
    "string_56": "WATER ABSORB$",
    "string_57": "ELECTRIC$",
    "string_58": "FORECAST$",
    "string_59": "SERENE GRACE$",
    "string_60": "POISON$",
    "string_61": "POISON POINT$",
    "string_62": "DRAGON$",
    "string_63": "TRACE$",
    "string_64": "OBLIVIOUS$",
    "string_65": "TRUANT$",
    "string_66": "RUN AWAY$",
    "string_67": "STICKY HOLD$",
    "string_68": "CLOUD NINE$",
    "string_69": "NORMAL$",
    "string_70": "STEEL$",
    "string_71": "ILLUMINATE$",
    "string_72": "EARLY BIRD$",
    "string_73": "HUSTLE$",
    "string_74": "SHINE$",
    "string_75": "FLYING$",
    "string_76": "DROUGHT$",
    "string_77": "LIGHTNINGROD$",
    "string_78": "COMPOUNDEYES$",
    "string_79": "MARVEL SCALE$",
    "string_80": "WONDER GUARD$",
    "string_81": "INSOMNIA$",
    "string_82": "LEVITATE$",
    "string_83": "PLUS$",
    "string_84": "PRESSURE$",
    "string_85": "LIQUID OOZE$",
    "string_86": "COLOR CHANGE$",
    "string_87": "SOUNDPROOF$",
    "string_88": "EFFECT SPORE$",
    "string_89": "{PK}RS$",
    "string_90": "FIRE$",
    "string_91": "FLAME BODY$",
    "string_92": "MINUS$",
    "string_93": "OWN TEMPO$",
    "string_94": "MAGMA ARMOR$",
    "string_95": "WATER$",
    "string_96": "WATER VEIL$",
    "string_97": "BUG$",
    "string_98": "SWARM$",
    "string_99": "CUTE CHARM$",
    "string_100": "IMMUNITY$",
    "string_101": "BLAZE$",
    "string_102": "PICKUP$",
    "string_103": "PATTERN$",
    "string_104": "FLASH FIRE$",
    "string_105": "VITAL SPIRIT$",
    "string_106": "CHLOROPHYLL$",
    "string_107": "PURE POWER$",
    "string_108": "SHIELD DUST$",
    "string_109": "UNLICHT$",
    "string_110": "DUFTNOTE$",
    "string_111": "SPECKSCHICHT$",
    "string_112": "REGENGENUSS$",
    "string_113": "NIESEL$",
    "string_114": "AUSWEGLOS$",
    "string_115": "BEDROHER$",
    "string_116": "STEINHAUPT$",
    "string_117": "FARBE$",
    "string_118": "ALT. FARBE$",
    "string_119": "GESTEIN$",
    "string_120": "SCHÖN$",
    "string_121": "SCHÖNHEIT$",
    "string_122": "KLIMASCHUTZ$",
    "string_123": "PSYCHO$",
    "string_124": "SCHERENMACHT$",
    "string_125": "KAMPF$",
    "string_126": "WEGSPERRE$",
    "string_127": "KLUG$",
    "string_128": "KLUGHEIT$",
    "string_129": "TEMPOSCHUB$",
    "string_130": "COOL$",
    "string_131": "COOLNESS$",
    "string_132": "KAMPFPANZER$",
    "string_133": "ANMUTIG$",
    "string_134": "ANMUT$",
    "string_135": "ROBUSTHEIT$",
    "string_136": "SAUGNAPF$",
    "string_137": "PFLANZE$",
    "string_138": "NEUTRALTORSO$",
    "string_139": "STURZBACH$",
    "string_140": "GEIST$",
    "string_141": "EIS$",
    "string_142": "ADRENALIN$",
    "string_143": "RAUHAUT$",
    "string_144": "PANZERHAUT$",
    "string_145": "INNERE KRAFT$",
    "string_146": "FEUCHTIGKEIT$",
    "string_147": "BODEN$",
    "string_148": "FLEXIBILITÄT$",
    "string_149": "MAGNETFALLE$",
    "string_150": "PULVERRAUCH$",
    "string_151": "SYNCHRO$",
    "string_152": "NOTDÜNGER$",
    "string_153": "WASSERTEMPO$",
    "string_154": "SANDSTURM$",
    "string_155": "SANDSCHLEIER$",
    "string_156": "ADLERAUGE$",
    "string_157": "KONZENTRATOR$",
    "string_158": "STATIK$",
    "string_159": "TYP$",
    "string_160": "STARK$",
    "string_161": "STÄRKE$",
    "string_162": "EXPIDERMIS$",
    "string_163": "KRAFTKOLOSS$",
    "string_164": "VOLTABSORBER$",
    "string_165": "H2O-ABSORBER$",
    "string_166": "ELEKTRO$",
    "string_167": "PROGNOSE$",
    "string_168": "EDELMUT$",
    "string_169": "GIFT$",
    "string_170": "GIFTDORN$",
    "string_171": "DRACHEN$",
    "string_172": "FÄHRTE$",
    "string_173": "DÖSIGKEIT$",
    "string_174": "SCHNARCHNASE$",
    "string_175": "ANGSTHASE$",
    "string_176": "WERTEHALTER$",
    "string_177": "WOLKE SIEBEN$",
    "string_178": "NORMAL$",
    "string_179": "STAHL$",
    "string_180": "ERLEUCHTUNG$",
    "string_181": "FRÜHWECKER$",
    "string_182": "ÜBEREIFER$",
    "string_183": "SCHEINEN$",
    "string_184": "FLIEGEN$",
    "string_185": "DÜRRE$",
    "string_186": "BLITZFÄNGER$",
    "string_187": "FACETTENAUGE$",
    "string_188": "NOTSCHUTZ$",
    "string_189": "WUNDERWACHE$",
    "string_190": "INSOMNIA$",
    "string_191": "SCHWEBE$",
    "string_192": "PLUS$",
    "string_193": "ERZWINGER$",
    "string_194": "KLOAKENSOSSE$",
    "string_195": "FARBWECHSEL$",
    "string_196": "LÄRMSCHUTZ$",
    "string_197": "SPORENWIRT$",
    "string_198": "POKéRUS$",
    "string_199": "FEUER$",
    "string_200": "FLAMMKÖRPER$",
    "string_201": "MINUS$",
    "string_202": "TEMPOMACHER$",
    "string_203": "MAGMAPANZER$",
    "string_204": "WASSER$",
    "string_205": "AQUAHÜLLE$",
    "string_206": "KÄFER$",
    "string_207": "HEXAPLAGA$",
    "string_208": "CHARMEBOLZEN$",
    "string_209": "IMMUNITÄT$",
    "string_210": "GROSSBRAND$",
    "string_211": "MITNAHME$",
    "string_212": "MUSTER$",
    "string_213": "FEUERFÄNGER$",
    "string_214": "MUNTERKEIT$",
    "string_215": "CHLOROPHYLL$",
    "string_216": "MENTALKRAFT$",
    "string_217": "PUDERABWEHR$"
  }
}